crash-0.31.5-py3.12-nspkg.pth
crate/crash/__init__.py
crate/crash/__main__.py
crate/crash/command.py
crate/crash/commands.py
crate/crash/config.py
crate/crash/connect.txt
crate/crash/keybinding.py
crate/crash/layout.py
crate/crash/output.txt
crate/crash/outputs.py
crate/crash/printer.py
crate/crash/repl.py
crate/crash/sysinfo.py
crate/crash/tabulate.py
crash-0.31.5.dist-info/LICENSE
crash-0.31.5.dist-info/METADATA
crash-0.31.5.dist-info/NOTICE
crash-0.31.5.dist-info/WHEEL
crash-0.31.5.dist-info/entry_points.txt
crash-0.31.5.dist-info/namespace_packages.txt
crash-0.31.5.dist-info/top_level.txt
crash-0.31.5.dist-info/RECORD
