Metadata-Version: 2.1
Name: crash
Version: 0.31.5
Summary: CrateDB Shell
Home-page: https://github.com/crate/crash
Author: Crate.io
Author-email: office@crate.io
License: Apache License 2.0
Keywords: crate db data client shell
Platform: any
Classifier: Development Status :: 5 - Production/Stable
Classifier: Intended Audience :: Developers
Classifier: License :: OSI Approved :: Apache Software License
Classifier: Operating System :: OS Independent
Classifier: Programming Language :: Python
Classifier: Programming Language :: Python :: 3
Classifier: Programming Language :: Python :: 3.7
Classifier: Programming Language :: Python :: 3.8
Classifier: Programming Language :: Python :: 3.9
Classifier: Programming Language :: Python :: 3.10
Classifier: Programming Language :: Python :: 3.11
Classifier: Programming Language :: Python :: 3.12
Classifier: Programming Language :: Python :: Implementation :: CPython
Classifier: Programming Language :: Python :: Implementation :: PyPy
Classifier: Topic :: Database
Requires-Python: >=3.7
License-File: LICENSE
License-File: NOTICE
Requires-Dist: colorama <1
Requires-Dist: Pygments <3,>=2.4
Requires-Dist: crate >=0.35.2
Requires-Dist: platformdirs <5
Requires-Dist: prompt-toolkit <4,>=3.0
Requires-Dist: tabulate <0.10,>=0.9
Requires-Dist: sqlparse <0.6.0,>=0.4.4
Requires-Dist: verlib2 <0.3
Provides-Extra: argcompletion
Requires-Dist: argcomplete ; extra == 'argcompletion'
Provides-Extra: devel
Requires-Dist: coverage <8 ; extra == 'devel'
Requires-Dist: flake8 <8 ; extra == 'devel'
Requires-Dist: isort <6 ; extra == 'devel'
Provides-Extra: test
Requires-Dist: crate[test] ; extra == 'test'
Requires-Dist: zc.customdoctests <2 ; extra == 'test'
Requires-Dist: cratedb-toolkit[test] ; extra == 'test'
